<HBProfile>
<Name>Kunlai Summit</Name>
<MinDurability>0.4</MinDurability>
<MinFreeBagSlots>1</MinFreeBagSlots>

<MinLevel>90</MinLevel>
<MaxLevel>100</MaxLevel>
<Factions>99999</Factions>

<MailGrey>False</MailGrey>
<MailWhite>True</MailWhite>
<MailGreen>True</MailGreen>
<MailBlue>True</MailBlue>
<MailPurple>True</MailPurple>
 
<SellGrey>True</SellGrey>
<SellWhite>false</SellWhite>
<SellGreen>False</SellGreen>
<SellBlue>False</SellBlue>
<SellPurple>False</SellPurple>

<Vendors>
<Vendor Name="Supplier Xin" Entry="62737" Type="Repair" X="2419.361" Y="3007.01" Z="417.3719" />
</Vendors>

<Mailboxes>
<Mailbox X="2352.375" Y="2994.757" Z="421.2402" />
</Mailboxes>

<Hotspots>
<Hotspot X="3967.944" Y="2338.127" Z="647.3362" />
<Hotspot X="3941.571" Y="2301.199" Z="668.3308" />
<Hotspot X="3915.198" Y="2264.271" Z="731.8268" />
<Hotspot X="3851.902" Y="2175.644" Z="884.218" />
<Hotspot X="3820.254" Y="2131.331" Z="947.5245" />
<Hotspot X="3780.694" Y="2075.938" Z="972.2389" />
<Hotspot X="3754.321" Y="2039.01" Z="969.7756" />
<Hotspot X="3727.948" Y="2002.083" Z="967.3123" />
<Hotspot X="3701.575" Y="1965.154" Z="964.8489" />
<Hotspot X="3672.564" Y="1924.534" Z="962.1392" />
<Hotspot X="3646.191" Y="1887.606" Z="959.6759" />
<Hotspot X="3619.818" Y="1850.678" Z="954.1082" />
<Hotspot X="3593.445" Y="1813.75" Z="948.5404" />
<Hotspot X="3590.712" Y="1809.924" Z="947.6353" />
<Hotspot X="3607.368" Y="1762.869" Z="976.8062" />
<Hotspot X="3624.024" Y="1715.813" Z="982.8345" />
<Hotspot X="3640.679" Y="1668.758" Z="975.946" />
<Hotspot X="3665.663" Y="1598.175" Z="965.0114" />
<Hotspot X="3682.318" Y="1551.12" Z="957.7216" />
<Hotspot X="3698.974" Y="1504.065" Z="950.4318" />
<Hotspot X="3715.629" Y="1457.01" Z="943.142" />
<Hotspot X="3737.282" Y="1395.838" Z="933.6653" />
<Hotspot X="3753.937" Y="1348.783" Z="926.3755" />
<Hotspot X="3770.593" Y="1301.727" Z="919.0857" />
<Hotspot X="3780.997" Y="1272.333" Z="914.532" />
<Hotspot X="3711.344" Y="1265.386" Z="914.0939" />
<Hotspot X="3661.592" Y="1260.424" Z="913.781" />
<Hotspot X="3611.84" Y="1255.462" Z="913.4681" />
<Hotspot X="3557.113" Y="1250.004" Z="913.1239" />
<Hotspot X="3507.36" Y="1245.042" Z="912.811" />
<Hotspot X="3442.683" Y="1238.591" Z="912.4042" />
<Hotspot X="3442.156" Y="1238.538" Z="912.4009" />
<Hotspot X="3410.23" Y="1295.01" Z="922.564" />
<Hotspot X="3385.672" Y="1338.449" Z="963.3457" />
<Hotspot X="3346.379" Y="1407.952" Z="1028.596" />
<Hotspot X="3319.365" Y="1455.735" Z="1039.016" />
<Hotspot X="3280.071" Y="1525.239" Z="999.2344" />
<Hotspot X="3255.512" Y="1568.678" Z="974.3707" />
<Hotspot X="3230.954" Y="1612.117" Z="949.5071" />
<Hotspot X="3206.396" Y="1655.557" Z="924.6434" />
<Hotspot X="3181.837" Y="1698.996" Z="899.7798" />
<Hotspot X="3158.398" Y="1740.456" Z="876.0491" />
<Hotspot X="3122.44" Y="1709.363" Z="860.5491" />
<Hotspot X="3068.504" Y="1662.723" Z="837.2991" />
<Hotspot X="3032.546" Y="1631.63" Z="821.799" />
<Hotspot X="2996.589" Y="1600.536" Z="806.2991" />
<Hotspot X="2949.844" Y="1560.115" Z="786.149" />
<Hotspot X="2906.694" Y="1522.803" Z="767.549" />
<Hotspot X="2870.737" Y="1491.71" Z="752.049" />
<Hotspot X="2834.779" Y="1460.616" Z="736.549" />
<Hotspot X="2798.822" Y="1429.523" Z="721.049" />
<Hotspot X="2787.843" Y="1420.03" Z="716.3167" />
<Hotspot X="2795.142" Y="1469.492" Z="716.8134" />
<Hotspot X="2802.44" Y="1518.954" Z="720.358" />
<Hotspot X="2809.738" Y="1568.416" Z="723.9026" />
<Hotspot X="2817.037" Y="1617.878" Z="723.731" />
<Hotspot X="2824.335" Y="1667.34" Z="723.5595" />
<Hotspot X="2831.633" Y="1716.802" Z="723.3879" />
<Hotspot X="2838.931" Y="1766.264" Z="723.2164" />
<Hotspot X="2848.419" Y="1830.564" Z="722.9934" />
<Hotspot X="2857.907" Y="1894.865" Z="722.7704" />
<Hotspot X="2865.206" Y="1944.327" Z="722.5989" />
<Hotspot X="2872.504" Y="1993.789" Z="722.4273" />
<Hotspot X="2876.309" Y="2019.578" Z="722.3379" />
<Hotspot X="2827.108" Y="2068.725" Z="730.3281" />
<Hotspot X="2791.964" Y="2103.83" Z="743.577" />
<Hotspot X="2756.82" Y="2138.934" Z="756.826" />
<Hotspot X="2721.677" Y="2174.039" Z="770.075" />
<Hotspot X="2686.533" Y="2209.144" Z="783.324" />
<Hotspot X="2651.389" Y="2244.249" Z="796.573" />
<Hotspot X="2616.245" Y="2279.353" Z="809.8219" />
<Hotspot X="2581.102" Y="2314.458" Z="823.0709" />
<Hotspot X="2535.415" Y="2360.094" Z="840.2946" />
<Hotspot X="2500.271" Y="2395.199" Z="824.3143" />
<Hotspot X="2465.127" Y="2430.304" Z="808.3342" />
<Hotspot X="2433.98" Y="2461.417" Z="794.1711" />
<Hotspot X="2482.065" Y="2450.563" Z="810.7377" />
<Hotspot X="2530.151" Y="2439.709" Z="832.5591" />
<Hotspot X="2578.237" Y="2428.856" Z="851.2675" />
<Hotspot X="2736.919" Y="2393.039" Z="869.2306" />
<Hotspot X="2794.622" Y="2380.015" Z="875.7626" />
<Hotspot X="2842.708" Y="2369.161" Z="881.206" />
<Hotspot X="2962.922" Y="2342.027" Z="894.8144" />
<Hotspot X="3011.008" Y="2331.173" Z="900.2578" />
<Hotspot X="3104.97" Y="2309.965" Z="910.8944" />
<Hotspot X="3123.267" Y="2351.865" Z="895.0695" />
<Hotspot X="3141.563" Y="2393.766" Z="881.1289" />
<Hotspot X="3159.86" Y="2435.667" Z="867.1882" />
<Hotspot X="3201.942" Y="2532.038" Z="835.1246" />
<Hotspot X="3238.535" Y="2615.839" Z="783.4976" />
<Hotspot X="3260.491" Y="2666.12" Z="752.5212" />
<Hotspot X="3284.277" Y="2720.59" Z="718.9636" />
<Hotspot X="3302.573" Y="2762.491" Z="693.15" />
<Hotspot X="3305.285" Y="2768.7" Z="689.3246" />
<Hotspot X="3325.559" Y="2726.447" Z="718.1097" />
<Hotspot X="3343.99" Y="2688.034" Z="752.0416" />
<Hotspot X="3362.42" Y="2649.622" Z="785.9732" />
<Hotspot X="3380.851" Y="2611.209" Z="819.905" />
<Hotspot X="3399.282" Y="2572.797" Z="853.8366" />
<Hotspot X="3434.301" Y="2499.813" Z="918.3071" />
<Hotspot X="3452.732" Y="2461.401" Z="937.2669" />
<Hotspot X="3471.163" Y="2422.988" Z="956.2269" />
<Hotspot X="3489.594" Y="2384.576" Z="975.1868" />
<Hotspot X="3546.729" Y="2265.497" Z="1033.962" />
<Hotspot X="3547.314" Y="2264.279" Z="1032.96" />
</Hotspots>
</HBProfile>
